PyBetterThreads/BetterThread.py
PyBetterThreads/__init__.py
PyBetterThreads-0.0.3.dist-info/LICENSE
PyBetterThreads-0.0.3.dist-info/METADATA
PyBetterThreads-0.0.3.dist-info/WHEEL
PyBetterThreads-0.0.3.dist-info/top_level.txt
PyBetterThreads-0.0.3.dist-info/RECORD
