Metadata-Version: 2.1
Name: PyBetterThreads
Version: 0.0.3
Summary: Threads, but with more features!
Home-page: https://github.com/theAbdoSabbagh/PyBetterThreads
Author: theAbdoSabbagh
License: MIT
Project-URL: Documentation, https://github.com/theAbdoSabbagh/PyBetterThreads/blob/main/README.md
Project-URL: Issue tracker, https://github.com/theAbdoSabbagh/PyBetterThreads/issues
Classifier: Development Status :: 5 - Production/Stable
Classifier: License :: OSI Approved :: MIT License
Classifier: Intended Audience :: Developers
Classifier: Natural Language :: English
Classifier: Operating System :: OS Independent
Classifier: Programming Language :: Python :: 3.8
Classifier: Programming Language :: Python :: 3.9
Classifier: Programming Language :: Python :: 3.10
Classifier: Programming Language :: Python :: 3.11
Classifier: Programming Language :: Python :: 3.12
Classifier: Topic :: Internet
Classifier: Topic :: Software Development :: Libraries
Classifier: Topic :: Software Development :: Libraries :: Python Modules
Classifier: Topic :: Utilities
Classifier: Typing :: Typed
Requires-Python: >=3.8.0
License-File: LICENSE
